pipenv_poetry_migrate/__init__.py
pipenv_poetry_migrate/cli.py
pipenv_poetry_migrate/loader.py
pipenv_poetry_migrate/migrate.py
pipenv_poetry_migrate/translator.py
pipenv_poetry_migrate-0.7.0.dist-info/METADATA
pipenv_poetry_migrate-0.7.0.dist-info/WHEEL
pipenv_poetry_migrate-0.7.0.dist-info/entry_points.txt
pipenv_poetry_migrate-0.7.0.dist-info/licenses/LICENSE
pipenv_poetry_migrate-0.7.0.dist-info/RECORD
