Metadata-Version: 2.4
Name: pipenv-poetry-migrate
Version: 0.7.0
Summary: simple migration script, migrate pipenv to poetry
License: Apache-2.0
License-File: LICENSE
Author: Yoshiyuki HINO
Author-email: yhinoz@gmail.com
Requires-Python: >=3.10,<4.0
Classifier: License :: OSI Approved :: Apache Software License
Classifier: Programming Language :: Python :: 3
Classifier: Programming Language :: Python :: 3.10
Classifier: Programming Language :: Python :: 3.11
Classifier: Programming Language :: Python :: 3.12
Classifier: Programming Language :: Python :: 3.13
Classifier: Programming Language :: Python :: 3.14
Requires-Dist: tomlkit (>=0.12.1,<0.14.0)
Requires-Dist: typer (>=0.9,<0.20)
Project-URL: Homepage, https://github.com/yhino/pipenv-poetry-migrate
Project-URL: Repository, https://github.com/yhino/pipenv-poetry-migrate
